telegrapy/__init__.py
telegrapy/bot.py
telegrapy/telegram.py
telegrapy/telegram_error.py
telegrapy/telegram_parser.py
telegrapy-0.1.dist-info/LICENSE
telegrapy-0.1.dist-info/METADATA
telegrapy-0.1.dist-info/WHEEL
telegrapy-0.1.dist-info/top_level.txt
telegrapy-0.1.dist-info/RECORD
