Metadata-Version: 2.1
Name: telegrapy
Version: 0.1
Summary: Telegram Bot API
Home-page: https://github.com/sudogene/telegrapy
Author: sudogene
Author-email: andywubby@gmail.com
License: MIT
Platform: UNKNOWN
Classifier: License :: OSI Approved :: MIT License
Classifier: Programming Language :: Python :: 3
Classifier: Programming Language :: Python :: 3.7
Requires-Dist: feedparser
Requires-Dist: html2text
